{"cameraMode":{"drawMode":0,"name":"Shaded","section":"Shading Mode"},"sceneLighting":true,"audioPlay":false,"sceneViewState":{"m_AlwaysRefresh":false,"showFog":true,"showSkybox":true,"showFlares":true,"showImageEffects":true,"showParticleSystems":true,"showVisualEffectGraphs":true,"m_FxEnabled":true},"in2DMode":false,"pivot":{"x":-7.884590148925781,"y":-38.28950881958008,"z":24.88349723815918},"rotation":{"x":0.48720216751098635,"y":-0.2215970903635025,"z":0.1294008493423462,"w":0.8347796201705933},"size":34.2272834777832,"orthographic":false}